src/constants.v
core/constants.v

src/memory/instruction_memory.v
`include "constants.v"

module instruction_memory (
    input wire clk,
    input wire reset,
    
    // Interface com o estágio IF
    input wire [31:0] addr,
    output reg [31:0] data_out,
    input wire read_en,
    
    // Interface de depuração/carregamento
    input wire debug_en,
    input wire [31:0] debug_addr,
    input wire [31:0] debug_data_in,
    input wire debug_write_en,
    output wire [31:0] debug_data_out
);

    // Memória organizada como 1024 palavras de 32 bits (4KB)
    reg [31:0] mem [0:1023];
    
    // Inicialização da memória com NOPs (addi x0, x0, 0)
    integer i;
    initial begin
        for (i = 0; i < 1024; i = i + 1) begin
            mem[i] = 32'h00000013; // NOP
        end
    end

    // Leitura normal (pelo estágio IF)
    always @(posedge clk) begin
        if (reset) begin
            data_out <= 32'h00000013; // Retorna NOP no reset
        end else if (read_en) begin
            // Alinhamento de endereço para palavras (addr[1:0] são ignorados)
            data_out <= mem[addr[31:2]];
        end
    end

    // Interface de depuração/carregamento (síncrona)
    assign debug_data_out = mem[debug_addr[31:2]];
    
    always @(posedge clk) begin
        if (debug_en && debug_write_en) begin
            mem[debug_addr[31:2]] <= debug_data_in;
        end
    end

    // Carregamento inicial de programa a partir de arquivo (para simulação)
    // Esta parte é usada apenas durante a simulação
`ifdef SIMULATION
    initial begin
        $readmemh("compiler/program.hex", mem);
    end
`endif

endmodule

tb/memory/tb_instruction_memory.v
`timescale 1ns/1ps
`include "constants.v"

module tb_instruction_memory;

    reg clk = 0;
    reg reset;
    reg [31:0] addr;
    wire [31:0] data_out;
    reg read_en;

    // Interface de debug
    reg debug_en;
    reg [31:0] debug_addr;
    reg [31:0] debug_data_in;
    reg debug_write_en;
    wire [31:0] debug_data_out;

    // Variável de iteração
    reg [31:0] i;

    // Clock
    always #5 clk = ~clk;

    // DUT
    instruction_memory dut (
        .clk(clk),
        .reset(reset),
        .addr(addr),
        .data_out(data_out),
        .read_en(read_en),
        .debug_en(debug_en),
        .debug_addr(debug_addr),
        .debug_data_in(debug_data_in),
        .debug_write_en(debug_write_en),
        .debug_data_out(debug_data_out)
    );

    // Checagem
    task check(string name, input [31:0] got, input [31:0] expected);
        begin
            if (got !== expected) begin
                $display("\033[1;31m[FAIL]\033[0m %s: Esperado 0x%h, Obteve 0x%h", name, expected, got);
            end else begin
                $display("\033[1;32m[PASS]\033[0m %s: Valor 0x%h", name, got);
            end
        end
    endtask

    initial begin
        // Dump para GTKWave
        $dumpfile("dump.vcd");
        $dumpvars(0, tb_instruction_memory);
        
        // Dump manual de parte da memória
        $display("\n---- DUMP INICIAL DAS PRIMEIRAS INSTRUÇÕES ----");
        for (i = 0; i < 8; i = i + 1) begin
            $display("mem[%0d] = %h", i, dut.mem[i]);
        end
        
        $display("-----------------------------------------------\n");

        $display("\n---- TESTE INSTRUCTION_MEMORY ----\n");

        // Reset inicial
        reset = 1;
        read_en = 0;
        debug_en = 0;
        debug_write_en = 0;
        addr = 0;
        debug_addr = 0;
        debug_data_in = 0;

        #10;
        reset = 0;

        // -------------------------------
        // 1. Verifica se no reset sai NOP
        // -------------------------------
        addr = 32'h00000000;
        read_en = 1;
        #10;
        check("Reset retorna NOP", data_out, 32'h00000013);

        // -------------------------------
        // 2. Escreve via interface de debug
        // -------------------------------
        debug_en = 1;
        debug_write_en = 1;
        debug_addr = 32'h00000008; // palavra 2
        debug_data_in = 32'hCAFEBABE;
        #10;

        // -------------------------------
        // 3. Lê instrução via porta normal
        // -------------------------------
        read_en = 1;
        addr = 32'h00000008; // mesma posição
        debug_write_en = 0;
        #10;
        check("Leitura normal após escrita debug", data_out, 32'hCAFEBABE);

        // -------------------------------
        // 4. Lê via debug_data_out
        // -------------------------------
        check("Leitura via debug_data_out", debug_data_out, 32'hCAFEBABE);

        // -------------------------------
        // 5. Escrita sem debug_en = deve ser ignorada
        // -------------------------------
        debug_en = 0;
        debug_write_en = 1;
        debug_addr = 32'h0000000C;
        debug_data_in = 32'hDEADBEEF;
        #10;

        addr = 32'h0000000C;
        read_en = 1;
        #10;
        check("Escrita ignorada sem debug_en", data_out, 32'h00000013); // deve continuar sendo NOP

        $display("\n---- FIM DOS TESTES ----\n");
        $finish;
        
    end
    

endmodule

dump.vcd
$date
	Wed Jul 30 15:35:57 2025
$end
$version
	Icarus Verilog
$end
$timescale
	1ps
$end
$scope module tb_instruction_memory $end
$var wire 32 ! debug_data_out [31:0] $end
$var wire 32 " data_out [31:0] $end
$var reg 32 # addr [31:0] $end
$var reg 1 $ clk $end
$var reg 32 % debug_addr [31:0] $end
$var reg 32 & debug_data_in [31:0] $end
$var reg 1 ' debug_en $end
$var reg 1 ( debug_write_en $end
$var reg 32 ) i [31:0] $end
$var reg 1 * read_en $end
$var reg 1 + reset $end
$scope module dut $end
$var wire 32 , addr [31:0] $end
$var wire 1 $ clk $end
$var wire 32 - debug_addr [31:0] $end
$var wire 32 . debug_data_in [31:0] $end
$var wire 32 / debug_data_out [31:0] $end
$var wire 1 ' debug_en $end
$var wire 1 ( debug_write_en $end
$var wire 1 * read_en $end
$var wire 1 + reset $end
$var reg 32 0 data_out [31:0] $end
$var integer 32 1 i [31:0] $end
$upscope $end
$scope task check $end
$var reg 32 2 expected [31:0] $end
$var reg 32 3 got [31:0] $end
$upscope $end
$upscope $end
$enddefinitions $end
$comment Show the parameter values. $end
$dumpall
$end
#0
$dumpvars
bx 3
bx 2
b10000000000 1
bx 0
b1100010000000010110011 /
b0 .
b0 -
b0 ,
1+
0*
b1000 )
0(
0'
b0 &
b0 %
0$
b0 #
bx "
b1100010000000010110011 !
$end
#5000
b10011 "
b10011 0
1$
#10000
0$
1*
0+
#15000
b1100010000000010110011 "
b1100010000000010110011 0
1$
#20000
b100000000000011101111 !
b100000000000011101111 /
0$
b11001010111111101011101010111110 &
b11001010111111101011101010111110 .
b1000 %
b1000 -
1(
1'
b10011 2
b1100010000000010110011 3
#25000
b11001010111111101011101010111110 !
b11001010111111101011101010111110 /
1$
#30000
0$
0(
b1000 #
b1000 ,
#35000
b11001010111111101011101010111110 "
b11001010111111101011101010111110 0
1$
#40000
b10011 !
b10011 /
0$
b11011110101011011011111011101111 &
b11011110101011011011111011101111 .
b1100 %
b1100 -
1(
0'
b11001010111111101011101010111110 2
b11001010111111101011101010111110 3
#45000
1$
#50000
0$
b1100 #
b1100 ,
#55000
b10011 "
b10011 0
1$
#60000
0$
b10011 2
b10011 3
